pysurrealdb/__init__.py
pysurrealdb/clients/http_client.py
pysurrealdb/clients/ws_client.py
pysurrealdb/config.py
pysurrealdb/connections.py
pysurrealdb/cursor.py
pysurrealdb/err.py
pysurrealdb/model.py
pysurrealdb/query_builder.py
pysurrealdb/tests/__init__.py
pysurrealdb/tests/mytests.py
pysurrealdb/tests/python.log
pysurrealdb/tests/test_connection_http.py
pysurrealdb/tests/test_connection_ws.py
pysurrealdb/utils.py
pysurrealdb-0.3.2.dist-info/LICENSE
pysurrealdb-0.3.2.dist-info/WHEEL
pysurrealdb-0.3.2.dist-info/METADATA
pysurrealdb-0.3.2.dist-info/RECORD
