Metadata-Version: 2.1
Name: pysurrealdb
Version: 0.3.2
Summary: A library to connect to SurrealDB.
License: MIT
Author: Aurelion314
Requires-Python: >=3.7,<4.0
Classifier: License :: OSI Approved :: MIT License
Classifier: Programming Language :: Python :: 3
Classifier: Programming Language :: Python :: 3.10
Classifier: Programming Language :: Python :: 3.7
Classifier: Programming Language :: Python :: 3.8
Classifier: Programming Language :: Python :: 3.9
Requires-Dist: requests
